src/2captcha-solver/__init__.py
src/2captcha-solver/setup.py
src/2captcha-solver/examples/__init__.py
src/2captcha-solver/examples/canvas.py
src/2captcha-solver/examples/canvas_base64.py
src/2captcha-solver/examples/canvas_options.py
src/2captcha-solver/examples/capy.py
src/2captcha-solver/examples/capy_options.py
src/2captcha-solver/examples/coordinates.py
src/2captcha-solver/examples/coordinates_base64.py
src/2captcha-solver/examples/coordinates_options.py
src/2captcha-solver/examples/funcaptcha.py
src/2captcha-solver/examples/funcaptcha_options.py
src/2captcha-solver/examples/geetest.py
src/2captcha-solver/examples/geetest_options.py
src/2captcha-solver/examples/grid.py
src/2captcha-solver/examples/grid_base64.py
src/2captcha-solver/examples/grid_options.py
src/2captcha-solver/examples/hcaptcha.py
src/2captcha-solver/examples/hcaptcha_options.py
src/2captcha-solver/examples/keycaptcha.py
src/2captcha-solver/examples/keycaptcha_options.py
src/2captcha-solver/examples/normal.py
src/2captcha-solver/examples/normal_base64.py
src/2captcha-solver/examples/normal_options.py
src/2captcha-solver/examples/recaptcha_v2.py
src/2captcha-solver/examples/recaptcha_v2_options.py
src/2captcha-solver/examples/recaptcha_v3.py
src/2captcha-solver/examples/recaptcha_v3_options.py
src/2captcha-solver/examples/rotate.py
src/2captcha-solver/examples/rotate_options.py
src/2captcha-solver/examples/text.py
src/2captcha-solver/examples/text_options.py
src/2captcha-solver/twocaptcha/__init__.py
src/2captcha-solver/twocaptcha/api.py
src/2captcha-solver/twocaptcha/solver.py
venv/bin/activate_this.py
venv/bin/rst2html.py
venv/bin/rst2html4.py
venv/bin/rst2html5.py
venv/bin/rst2latex.py
venv/bin/rst2man.py
venv/bin/rst2odt.py
venv/bin/rst2odt_prepstyles.py
venv/bin/rst2pseudoxml.py
venv/bin/rst2s5.py
venv/bin/rst2xetex.py
venv/bin/rst2xml.py
venv/bin/rstpep2html.py
venv/lib/python3.8/site-packages/_virtualenv.py
venv/lib/python3.8/site-packages/six.py
2captcha_solver-1.1.1.dist-info/METADATA
2captcha_solver-1.1.1.dist-info/WHEEL
2captcha_solver-1.1.1.dist-info/licenses/LICENSE
2captcha_solver-1.1.1.dist-info/RECORD
