Metadata-Version: 2.1
Name: 2captcha-solver
Version: 1.1.1
Summary: Python module for easy integration with 2Captcha API'
Project-URL: Homepage, https://github.com/2captchacom/2captcha-python
Project-URL: Bug Tracker, https://github.com/2captchacom/2captcha-python/issues
Author-email: 2Captcha <info@2captcha.com>
License-File: LICENSE
Classifier: License :: OSI Approved :: MIT License
Classifier: Operating System :: OS Independent
Classifier: Programming Language :: Python :: 3
Requires-Python: >=3.6
